{"is_source_file": true, "format": "Python", "description": "This file defines API endpoints for managing organization branding settings, including retrieving and updating branding data such as logo URLs, colors, and organization names, using FastAPI and SQLAlchemy.", "external_files": ["src.api.models", "src.api.schemas", "src.api.auth"], "external_methods": ["get_db", "get_current_user", "rbac_required", "db.query", "db.commit", "db.refresh"], "published": ["router"], "classes": [{"name": "BrandingSettings", "description": "Schema/model representing branding settings data for organizations."}], "methods": [{"name": "get_branding( org_id: int, db: Session = Depends(get_db), current_user: User = Depends(get_current_user), )", "description": "Handles GET requests to retrieve branding settings for a specific organization.", "scope": "", "scopeKind": ""}, {"name": "update_branding( org_id: int, branding: BrandingSettings, db: Session = Depends(get_db), current_user: User = Depends(rbac_required(\"Super Admin\", \"State Admin\", \"District Admin\", \"Branch Admin\")), )", "description": "Handles PUT requests to update branding settings for a specific organization.", "scope": "", "scopeKind": ""}], "calls": ["db.query(Org).filter(Org.id == org_id).first", "db.commit()", "db.refresh(org)"], "search-terms": ["branding endpoints", "organization branding", "Logo and color CRUD", "FastAPI router branding"], "state": 2, "file_id": 16, "knowledge_revision": 51, "git_revision": "056e0c073407afc291d0fb32708f07b801664f42", "revision_history": [{"47": ""}, {"51": "056e0c073407afc291d0fb32708f07b801664f42"}], "ctags": [{"_type": "tag", "name": "get_branding", "path": "/home/kavia/workspace/code-generation/membersphere-platform-22477-22482/membership_backend/src/api/branding.py", "pattern": "/^def get_branding($/", "language": "Python", "kind": "function", "signature": "( org_id: int, db: Session = Depends(get_db), current_user: User = Depends(get_current_user), )"}, {"_type": "tag", "name": "router", "path": "/home/kavia/workspace/code-generation/membersphere-platform-22477-22482/membership_backend/src/api/branding.py", "pattern": "/^router = APIRouter(prefix=\"\\/branding\", tags=[\"Branding\"])$/", "language": "Python", "kind": "variable"}, {"_type": "tag", "name": "update_branding", "path": "/home/kavia/workspace/code-generation/membersphere-platform-22477-22482/membership_backend/src/api/branding.py", "pattern": "/^def update_branding($/", "language": "Python", "kind": "function", "signature": "( org_id: int, branding: BrandingSettings, db: Session = Depends(get_db), current_user: User = Depends(rbac_required(\"Super Admin\", \"State Admin\", \"District Admin\", \"Branch Admin\")), )"}], "hash": "883a1b8c9300f79289f35f48002bf325", "format-version": 4, "code-base-name": "membership_backend", "filename": "membership_backend/src/api/branding.py", "fields": [{"name": "router = APIRouter(prefix=\"\\/branding\", tags=[\"Branding\"])", "scope": "", "scopeKind": "", "description": "unavailable"}]}